caophim/__init__.py
caophim/conf.py
caophim/settings.py
caophim/urls.py
caophim/wsgi.py
main/__init__.py
main/admin.py
main/apps.py
main/migrations/0001_initial.py
main/migrations/__init__.py
main/models.py
main/tests.py
caophim-0.1.0.dist-info/entry_points.txt
caophim-0.1.0.dist-info/WHEEL
caophim-0.1.0.dist-info/METADATA
caophim-0.1.0.dist-info/RECORD
