Metadata-Version: 2.1
Name: caophim
Version: 0.1.0
Summary: 
Author: Bùi Thành Nhân
Author-email: hi@imnhan.com
Requires-Python: >=3.7,<4.0
Classifier: Programming Language :: Python :: 3
Classifier: Programming Language :: Python :: 3.7
Requires-Dist: django (>=3.0,<4.0)
Requires-Dist: goodconf (>=1.0,<2.0)
Requires-Dist: gunicorn (>=20.0,<21.0)
Requires-Dist: psycopg2 (>=2.8,<3.0)
